{
  "format_version": "1.21.40",
  "minecraft:biome": {
    "description": {
      "identifier": "be:forest_edge"
    },
    "components": {
      "minecraft:climate": {
        "temperature": 0.65,
        "downfall": 0.65,
        "snow_accumulation": [
          0,
          0.1
        ],
        "ash": 0,
        "red_spores": 0,
        "white_ash": 0
      },
      "minecraft:overworld_height": {
        "noise_type": "default"
      },
      "minecraft:surface_parameters": {
        "sea_floor_depth": 5,
        "sea_floor_material": "minecraft:gravel",
        "foundation_material": "minecraft:stone",
        "mid_material": "minecraft:coarse_dirt",
        "top_material": "minecraft:grass_block",
        "sea_material": "minecraft:water"
      },
      "minecraft:overworld_generation_rules": {
        "generate_for_climates": [
          [
            "medium",
            6
          ],
          [
            "lukewarm",
            3
          ]
        ]
      },
      "minecraft:fog_appearance": {
        "fog_identifier": "be:old_growth_highlands_fog"
      },
      "minecraft:tags": {
        "tags": [
          "overworld",
          "forest",
          "be_terrain",
          "be_transition",
          "be_forest_edge"
        ]
      }
    }
  }
}
